[{"id":0,"address":{"country":"Russia","city":"Moscow","street":"Polyanka","house":6,"floor":4,"flat":1},"productList":[{"type":"Orange","price":1,"title":"апельсины","withBones":true},{"type":"Apple","price":1,"title":"яблоки","color":"green"}]},{"id":1,"address":{"country":"Russia","city":"Moscow","street":"Polyanka","house":6,"floor":4,"flat":2},"productList":[{"type":"Orange","price":1,"title":"апельсины","withBones":true},{"type":"Apple","price":1,"title":"яблоки","color":"green"}]},{"id":2,"address":{"country":"Russia","city":"Moscow","street":"Polyanka","house":6,"floor":4,"flat":3},"productList":[{"type":"Orange","price":1,"title":"апельсины","withBones":true},{"type":"Apple","price":1,"title":"яблоки","color":"green"}]},{"id":3,"address":{"country":"Russia","city":"Moscow","street":"Polyanka","house":6,"floor":4,"flat":4},"productList":[{"type":"Orange","price":1,"title":"апельсины","withBones":true},{"type":"Apple","price":1,"title":"яблоки","color":"green"}]},{"id":4,"address":{"country":"Russia","city":"Moscow","street":"Polyanka","house":6,"floor":4,"flat":5},"productList":[{"type":"Orange","price":1,"title":"апельсины","withBones":true},{"type":"Apple","price":1,"title":"яблоки","color":"green"}]},{"id":5,"address":{"country":"Russia","city":"Moscow","street":"Polyanka","house":6,"floor":4,"flat":6},"productList":[{"type":"Orange","price":1,"title":"апельсины","withBones":true},{"type":"Apple","price":1,"title":"яблоки","color":"green"}]},{"id":6,"address":{"country":"Russia","city":"Moscow","street":"Polyanka","house":6,"floor":4,"flat":7},"productList":[{"type":"Orange","price":1,"title":"апельсины","withBones":true},{"type":"Apple","price":1,"title":"яблоки","color":"green"}]},{"id":7,"address":{"country":"Russia","city":"Moscow","street":"Polyanka","house":6,"floor":4,"flat":8},"productList":[{"type":"Orange","price":1,"title":"апельсины","withBones":true},{"type":"Apple","price":1,"title":"яблоки","color":"green"}]},{"id":8,"address":{"country":"Russia","city":"Moscow","street":"Polyanka","house":6,"floor":4,"flat":9},"productList":[{"type":"Orange","price":1,"title":"апельсины","withBones":true},{"type":"Apple","price":1,"title":"яблоки","color":"green"}]},{"id":9,"address":{"country":"Russia","city":"Moscow","street":"Polyanka","house":6,"floor":4,"flat":10},"productList":[{"type":"Orange","price":1,"title":"апельсины","withBones":true},{"type":"Apple","price":1,"title":"яблоки","color":"green"}]},{"id":10,"address":{"country":"Russia","city":"Moscow","street":"Polyanka","house":6,"floor":4,"flat":11},"productList":[{"type":"Orange","price":1,"title":"апельсины","withBones":true},{"type":"Apple","price":1,"title":"яблоки","color":"green"}]},{"id":11,"address":{"country":"Russia","city":"Moscow","street":"Polyanka","house":6,"floor":4,"flat":12},"productList":[{"type":"Orange","price":1,"title":"апельсины","withBones":true},{"type":"Apple","price":1,"title":"яблоки","color":"green"}]},{"id":12,"address":{"country":"Russia","city":"Moscow","street":"Polyanka","house":6,"floor":4,"flat":13},"productList":[{"type":"Orange","price":1,"title":"апельсины","withBones":true},{"type":"Apple","price":1,"title":"яблоки","color":"green"}]},{"id":13,"address":{"country":"Russia","city":"Moscow","street":"Polyanka","house":6,"floor":4,"flat":14},"productList":[{"type":"Orange","price":1,"title":"апельсины","withBones":true},{"type":"Apple","price":1,"title":"яблоки","color":"green"}]},{"id":14,"address":{"country":"Russia","city":"Moscow","street":"Polyanka","house":6,"floor":4,"flat":15},"productList":[{"type":"Orange","price":1,"title":"апельсины","withBones":true},{"type":"Apple","price":1,"title":"яблоки","color":"green"}]},{"id":15,"address":{"country":"Russia","city":"Moscow","street":"Polyanka","house":6,"floor":4,"flat":16},"productList":[{"type":"Orange","price":1,"title":"апельсины","withBones":true},{"type":"Apple","price":1,"title":"яблоки","color":"green"}]},{"id":16,"address":{"country":"Russia","city":"Moscow","street":"Polyanka","house":6,"floor":4,"flat":17},"productList":[{"type":"Orange","price":1,"title":"апельсины","withBones":true},{"type":"Apple","price":1,"title":"яблоки","color":"green"}]},{"id":17,"address":{"country":"Russia","city":"Moscow","street":"Polyanka","house":6,"floor":4,"flat":18},"productList":[{"type":"Orange","price":1,"title":"апельсины","withBones":true},{"type":"Apple","price":1,"title":"яблоки","color":"green"}]},{"id":18,"address":{"country":"Russia","city":"Moscow","street":"Polyanka","house":6,"floor":4,"flat":19},"productList":[{"type":"Orange","price":1,"title":"апельсины","withBones":true},{"type":"Apple","price":1,"title":"яблоки","color":"green"}]},{"id":19,"address":{"country":"Russia","city":"Moscow","street":"Polyanka","house":6,"floor":4,"flat":20},"productList":[{"type":"Orange","price":1,"title":"апельсины","withBones":true},{"type":"Apple","price":1,"title":"яблоки","color":"green"}]},{"id":20,"address":{"country":"Russia","city":"Moscow","street":"Polyanka","house":6,"floor":4,"flat":21},"productList":[{"type":"Orange","price":1,"title":"апельсины","withBones":true},{"type":"Apple","price":1,"title":"яблоки","color":"green"}]},{"id":21,"address":{"country":"Russia","city":"Moscow","street":"Polyanka","house":6,"floor":4,"flat":22},"productList":[{"type":"Orange","price":1,"title":"апельсины","withBones":true},{"type":"Apple","price":1,"title":"яблоки","color":"green"}]},{"id":22,"address":{"country":"Russia","city":"Moscow","street":"Polyanka","house":6,"floor":4,"flat":23},"productList":[{"type":"Orange","price":1,"title":"апельсины","withBones":true},{"type":"Apple","price":1,"title":"яблоки","color":"green"}]},{"id":23,"address":{"country":"Russia","city":"Moscow","street":"Polyanka","house":6,"floor":4,"flat":24},"productList":[{"type":"Orange","price":1,"title":"апельсины","withBones":true},{"type":"Apple","price":1,"title":"яблоки","color":"green"}]},{"id":24,"address":{"country":"Russia","city":"Moscow","street":"Polyanka","house":6,"floor":4,"flat":25},"productList":[{"type":"Orange","price":1,"title":"апельсины","withBones":true},{"type":"Apple","price":1,"title":"яблоки","color":"green"}]},{"id":25,"address":{"country":"Russia","city":"Moscow","street":"Polyanka","house":6,"floor":4,"flat":26},"productList":[{"type":"Orange","price":1,"title":"апельсины","withBones":true},{"type":"Apple","price":1,"title":"яблоки","color":"green"}]},{"id":26,"address":{"country":"Russia","city":"Moscow","street":"Polyanka","house":6,"floor":4,"flat":27},"productList":[{"type":"Orange","price":1,"title":"апельсины","withBones":true},{"type":"Apple","price":1,"title":"яблоки","color":"green"}]},{"id":27,"address":{"country":"Russia","city":"Moscow","street":"Polyanka","house":6,"floor":4,"flat":28},"productList":[{"type":"Orange","price":1,"title":"апельсины","withBones":true},{"type":"Apple","price":1,"title":"яблоки","color":"green"}]},{"id":28,"address":{"country":"Russia","city":"Moscow","street":"Polyanka","house":6,"floor":4,"flat":29},"productList":[{"type":"Orange","price":1,"title":"апельсины","withBones":true},{"type":"Apple","price":1,"title":"яблоки","color":"green"}]},{"id":29,"address":{"country":"Russia","city":"Moscow","street":"Polyanka","house":6,"floor":4,"flat":30},"productList":[{"type":"Orange","price":1,"title":"апельсины","withBones":true},{"type":"Apple","price":1,"title":"яблоки","color":"green"}]},{"id":30,"address":{"country":"Russia","city":"Moscow","street":"Polyanka","house":6,"floor":4,"flat":31},"productList":[{"type":"Orange","price":1,"title":"апельсины","withBones":true},{"type":"Apple","price":1,"title":"яблоки","color":"green"}]},{"id":31,"address":{"country":"Russia","city":"Moscow","street":"Polyanka","house":6,"floor":4,"flat":32},"productList":[{"type":"Orange","price":1,"title":"апельсины","withBones":true},{"type":"Apple","price":1,"title":"яблоки","color":"green"}]},{"id":32,"address":{"country":"Russia","city":"Moscow","street":"Polyanka","house":6,"floor":4,"flat":33},"productList":[{"type":"Orange","price":1,"title":"апельсины","withBones":true},{"type":"Apple","price":1,"title":"яблоки","color":"green"}]},{"id":33,"address":{"country":"Russia","city":"Moscow","street":"Polyanka","house":6,"floor":4,"flat":34},"productList":[{"type":"Orange","price":1,"title":"апельсины","withBones":true},{"type":"Apple","price":1,"title":"яблоки","color":"green"}]},{"id":34,"address":{"country":"Russia","city":"Moscow","street":"Polyanka","house":6,"floor":4,"flat":35},"productList":[{"type":"Orange","price":1,"title":"апельсины","withBones":true},{"type":"Apple","price":1,"title":"яблоки","color":"green"}]},{"id":35,"address":{"country":"Russia","city":"Moscow","street":"Polyanka","house":6,"floor":4,"flat":36},"productList":[{"type":"Orange","price":1,"title":"апельсины","withBones":true},{"type":"Apple","price":1,"title":"яблоки","color":"green"}]},{"id":36,"address":{"country":"Russia","city":"Moscow","street":"Polyanka","house":6,"floor":4,"flat":37},"productList":[{"type":"Orange","price":1,"title":"апельсины","withBones":true},{"type":"Apple","price":1,"title":"яблоки","color":"green"}]},{"id":37,"address":{"country":"Russia","city":"Moscow","street":"Polyanka","house":6,"floor":4,"flat":38},"productList":[{"type":"Orange","price":1,"title":"апельсины","withBones":true},{"type":"Apple","price":1,"title":"яблоки","color":"green"}]},{"id":38,"address":{"country":"Russia","city":"Moscow","street":"Polyanka","house":6,"floor":4,"flat":39},"productList":[{"type":"Orange","price":1,"title":"апельсины","withBones":true},{"type":"Apple","price":1,"title":"яблоки","color":"green"}]},{"id":39,"address":{"country":"Russia","city":"Moscow","street":"Polyanka","house":6,"floor":4,"flat":40},"productList":[{"type":"Orange","price":1,"title":"апельсины","withBones":true},{"type":"Apple","price":1,"title":"яблоки","color":"green"}]},{"id":40,"address":{"country":"Russia","city":"Moscow","street":"Polyanka","house":6,"floor":4,"flat":41},"productList":[{"type":"Orange","price":1,"title":"апельсины","withBones":true},{"type":"Apple","price":1,"title":"яблоки","color":"green"}]},{"id":41,"address":{"country":"Russia","city":"Moscow","street":"Polyanka","house":6,"floor":4,"flat":42},"productList":[{"type":"Orange","price":1,"title":"апельсины","withBones":true},{"type":"Apple","price":1,"title":"яблоки","color":"green"}]},{"id":42,"address":{"country":"Russia","city":"Moscow","street":"Polyanka","house":6,"floor":4,"flat":43},"productList":[{"type":"Orange","price":1,"title":"апельсины","withBones":true},{"type":"Apple","price":1,"title":"яблоки","color":"green"}]},{"id":43,"address":{"country":"Russia","city":"Moscow","street":"Polyanka","house":6,"floor":4,"flat":44},"productList":[{"type":"Orange","price":1,"title":"апельсины","withBones":true},{"type":"Apple","price":1,"title":"яблоки","color":"green"}]},{"id":44,"address":{"country":"Russia","city":"Moscow","street":"Polyanka","house":6,"floor":4,"flat":45},"productList":[{"type":"Orange","price":1,"title":"апельсины","withBones":true},{"type":"Apple","price":1,"title":"яблоки","color":"green"}]},{"id":45,"address":{"country":"Russia","city":"Moscow","street":"Polyanka","house":6,"floor":4,"flat":46},"productList":[{"type":"Orange","price":1,"title":"апельсины","withBones":true},{"type":"Apple","price":1,"title":"яблоки","color":"green"}]},{"id":46,"address":{"country":"Russia","city":"Moscow","street":"Polyanka","house":6,"floor":4,"flat":47},"productList":[{"type":"Orange","price":1,"title":"апельсины","withBones":true},{"type":"Apple","price":1,"title":"яблоки","color":"green"}]},{"id":47,"address":{"country":"Russia","city":"Moscow","street":"Polyanka","house":6,"floor":4,"flat":48},"productList":[{"type":"Orange","price":1,"title":"апельсины","withBones":true},{"type":"Apple","price":1,"title":"яблоки","color":"green"}]},{"id":48,"address":{"country":"Russia","city":"Moscow","street":"Polyanka","house":6,"floor":4,"flat":49},"productList":[{"type":"Orange","price":1,"title":"апельсины","withBones":true},{"type":"Apple","price":1,"title":"яблоки","color":"green"}]},{"id":49,"address":{"country":"Russia","city":"Moscow","street":"Polyanka","house":6,"floor":4,"flat":50},"productList":[{"type":"Orange","price":1,"title":"апельсины","withBones":true},{"type":"Apple","price":1,"title":"яблоки","color":"green"}]},{"id":50,"address":{"country":"Russia","city":"Moscow","street":"Polyanka","house":6,"floor":4,"flat":51},"productList":[{"type":"Orange","price":1,"title":"апельсины","withBones":true},{"type":"Apple","price":1,"title":"яблоки","color":"green"}]},{"id":51,"address":{"country":"Russia","city":"Moscow","street":"Polyanka","house":6,"floor":4,"flat":52},"productList":[{"type":"Orange","price":1,"title":"апельсины","withBones":true},{"type":"Apple","price":1,"title":"яблоки","color":"green"}]},{"id":52,"address":{"country":"Russia","city":"Moscow","street":"Polyanka","house":6,"floor":4,"flat":53},"productList":[{"type":"Orange","price":1,"title":"апельсины","withBones":true},{"type":"Apple","price":1,"title":"яблоки","color":"green"}]},{"id":53,"address":{"country":"Russia","city":"Moscow","street":"Polyanka","house":6,"floor":4,"flat":54},"productList":[{"type":"Orange","price":1,"title":"апельсины","withBones":true},{"type":"Apple","price":1,"title":"яблоки","color":"green"}]},{"id":54,"address":{"country":"Russia","city":"Moscow","street":"Polyanka","house":6,"floor":4,"flat":55},"productList":[{"type":"Orange","price":1,"title":"апельсины","withBones":true},{"type":"Apple","price":1,"title":"яблоки","color":"green"}]},{"id":55,"address":{"country":"Russia","city":"Moscow","street":"Polyanka","house":6,"floor":4,"flat":56},"productList":[{"type":"Orange","price":1,"title":"апельсины","withBones":true},{"type":"Apple","price":1,"title":"яблоки","color":"green"}]},{"id":56,"address":{"country":"Russia","city":"Moscow","street":"Polyanka","house":6,"floor":4,"flat":57},"productList":[{"type":"Orange","price":1,"title":"апельсины","withBones":true},{"type":"Apple","price":1,"title":"яблоки","color":"green"}]},{"id":57,"address":{"country":"Russia","city":"Moscow","street":"Polyanka","house":6,"floor":4,"flat":58},"productList":[{"type":"Orange","price":1,"title":"апельсины","withBones":true},{"type":"Apple","price":1,"title":"яблоки","color":"green"}]},{"id":58,"address":{"country":"Russia","city":"Moscow","street":"Polyanka","house":6,"floor":4,"flat":59},"productList":[{"type":"Orange","price":1,"title":"апельсины","withBones":true},{"type":"Apple","price":1,"title":"яблоки","color":"green"}]},{"id":59,"address":{"country":"Russia","city":"Moscow","street":"Polyanka","house":6,"floor":4,"flat":60},"productList":[{"type":"Orange","price":1,"title":"апельсины","withBones":true},{"type":"Apple","price":1,"title":"яблоки","color":"green"}]},{"id":60,"address":{"country":"Russia","city":"Moscow","street":"Polyanka","house":6,"floor":4,"flat":61},"productList":[{"type":"Orange","price":1,"title":"апельсины","withBones":true},{"type":"Apple","price":1,"title":"яблоки","color":"green"}]},{"id":61,"address":{"country":"Russia","city":"Moscow","street":"Polyanka","house":6,"floor":4,"flat":62},"productList":[{"type":"Orange","price":1,"title":"апельсины","withBones":true},{"type":"Apple","price":1,"title":"яблоки","color":"green"}]},{"id":62,"address":{"country":"Russia","city":"Moscow","street":"Polyanka","house":6,"floor":4,"flat":63},"productList":[{"type":"Orange","price":1,"title":"апельсины","withBones":true},{"type":"Apple","price":1,"title":"яблоки","color":"green"}]},{"id":63,"address":{"country":"Russia","city":"Moscow","street":"Polyanka","house":6,"floor":4,"flat":64},"productList":[{"type":"Orange","price":1,"title":"апельсины","withBones":true},{"type":"Apple","price":1,"title":"яблоки","color":"green"}]},{"id":64,"address":{"country":"Russia","city":"Moscow","street":"Polyanka","house":6,"floor":4,"flat":65},"productList":[{"type":"Orange","price":1,"title":"апельсины","withBones":true},{"type":"Apple","price":1,"title":"яблоки","color":"green"}]},{"id":65,"address":{"country":"Russia","city":"Moscow","street":"Polyanka","house":6,"floor":4,"flat":66},"productList":[{"type":"Orange","price":1,"title":"апельсины","withBones":true},{"type":"Apple","price":1,"title":"яблоки","color":"green"}]},{"id":66,"address":{"country":"Russia","city":"Moscow","street":"Polyanka","house":6,"floor":4,"flat":67},"productList":[{"type":"Orange","price":1,"title":"апельсины","withBones":true},{"type":"Apple","price":1,"title":"яблоки","color":"green"}]},{"id":67,"address":{"country":"Russia","city":"Moscow","street":"Polyanka","house":6,"floor":4,"flat":68},"productList":[{"type":"Orange","price":1,"title":"апельсины","withBones":true},{"type":"Apple","price":1,"title":"яблоки","color":"green"}]},{"id":68,"address":{"country":"Russia","city":"Moscow","street":"Polyanka","house":6,"floor":4,"flat":69},"productList":[{"type":"Orange","price":1,"title":"апельсины","withBones":true},{"type":"Apple","price":1,"title":"яблоки","color":"green"}]},{"id":69,"address":{"country":"Russia","city":"Moscow","street":"Polyanka","house":6,"floor":4,"flat":70},"productList":[{"type":"Orange","price":1,"title":"апельсины","withBones":true},{"type":"Apple","price":1,"title":"яблоки","color":"green"}]},{"id":70,"address":{"country":"Russia","city":"Moscow","street":"Polyanka","house":6,"floor":4,"flat":71},"productList":[{"type":"Orange","price":1,"title":"апельсины","withBones":true},{"type":"Apple","price":1,"title":"яблоки","color":"green"}]},{"id":71,"address":{"country":"Russia","city":"Moscow","street":"Polyanka","house":6,"floor":4,"flat":72},"productList":[{"type":"Orange","price":1,"title":"апельсины","withBones":true},{"type":"Apple","price":1,"title":"яблоки","color":"green"}]},{"id":72,"address":{"country":"Russia","city":"Moscow","street":"Polyanka","house":6,"floor":4,"flat":73},"productList":[{"type":"Orange","price":1,"title":"апельсины","withBones":true},{"type":"Apple","price":1,"title":"яблоки","color":"green"}]},{"id":73,"address":{"country":"Russia","city":"Moscow","street":"Polyanka","house":6,"floor":4,"flat":74},"productList":[{"type":"Orange","price":1,"title":"апельсины","withBones":true},{"type":"Apple","price":1,"title":"яблоки","color":"green"}]},{"id":74,"address":{"country":"Russia","city":"Moscow","street":"Polyanka","house":6,"floor":4,"flat":75},"productList":[{"type":"Orange","price":1,"title":"апельсины","withBones":true},{"type":"Apple","price":1,"title":"яблоки","color":"green"}]},{"id":75,"address":{"country":"Russia","city":"Moscow","street":"Polyanka","house":6,"floor":4,"flat":76},"productList":[{"type":"Orange","price":1,"title":"апельсины","withBones":true},{"type":"Apple","price":1,"title":"яблоки","color":"green"}]},{"id":76,"address":{"country":"Russia","city":"Moscow","street":"Polyanka","house":6,"floor":4,"flat":77},"productList":[{"type":"Orange","price":1,"title":"апельсины","withBones":true},{"type":"Apple","price":1,"title":"яблоки","color":"green"}]},{"id":77,"address":{"country":"Russia","city":"Moscow","street":"Polyanka","house":6,"floor":4,"flat":78},"productList":[{"type":"Orange","price":1,"title":"апельсины","withBones":true},{"type":"Apple","price":1,"title":"яблоки","color":"green"}]},{"id":78,"address":{"country":"Russia","city":"Moscow","street":"Polyanka","house":6,"floor":4,"flat":79},"productList":[{"type":"Orange","price":1,"title":"апельсины","withBones":true},{"type":"Apple","price":1,"title":"яблоки","color":"green"}]},{"id":79,"address":{"country":"Russia","city":"Moscow","street":"Polyanka","house":6,"floor":4,"flat":80},"productList":[{"type":"Orange","price":1,"title":"апельсины","withBones":true},{"type":"Apple","price":1,"title":"яблоки","color":"green"}]},{"id":80,"address":{"country":"Russia","city":"Moscow","street":"Polyanka","house":6,"floor":4,"flat":81},"productList":[{"type":"Orange","price":1,"title":"апельсины","withBones":true},{"type":"Apple","price":1,"title":"яблоки","color":"green"}]},{"id":81,"address":{"country":"Russia","city":"Moscow","street":"Polyanka","house":6,"floor":4,"flat":82},"productList":[{"type":"Orange","price":1,"title":"апельсины","withBones":true},{"type":"Apple","price":1,"title":"яблоки","color":"green"}]},{"id":82,"address":{"country":"Russia","city":"Moscow","street":"Polyanka","house":6,"floor":4,"flat":83},"productList":[{"type":"Orange","price":1,"title":"апельсины","withBones":true},{"type":"Apple","price":1,"title":"яблоки","color":"green"}]},{"id":83,"address":{"country":"Russia","city":"Moscow","street":"Polyanka","house":6,"floor":4,"flat":84},"productList":[{"type":"Orange","price":1,"title":"апельсины","withBones":true},{"type":"Apple","price":1,"title":"яблоки","color":"green"}]},{"id":84,"address":{"country":"Russia","city":"Moscow","street":"Polyanka","house":6,"floor":4,"flat":85},"productList":[{"type":"Orange","price":1,"title":"апельсины","withBones":true},{"type":"Apple","price":1,"title":"яблоки","color":"green"}]},{"id":85,"address":{"country":"Russia","city":"Moscow","street":"Polyanka","house":6,"floor":4,"flat":86},"productList":[{"type":"Orange","price":1,"title":"апельсины","withBones":true},{"type":"Apple","price":1,"title":"яблоки","color":"green"}]},{"id":86,"address":{"country":"Russia","city":"Moscow","street":"Polyanka","house":6,"floor":4,"flat":87},"productList":[{"type":"Orange","price":1,"title":"апельсины","withBones":true},{"type":"Apple","price":1,"title":"яблоки","color":"green"}]},{"id":87,"address":{"country":"Russia","city":"Moscow","street":"Polyanka","house":6,"floor":4,"flat":88},"productList":[{"type":"Orange","price":1,"title":"апельсины","withBones":true},{"type":"Apple","price":1,"title":"яблоки","color":"green"}]},{"id":88,"address":{"country":"Russia","city":"Moscow","street":"Polyanka","house":6,"floor":4,"flat":89},"productList":[{"type":"Orange","price":1,"title":"апельсины","withBones":true},{"type":"Apple","price":1,"title":"яблоки","color":"green"}]},{"id":89,"address":{"country":"Russia","city":"Moscow","street":"Polyanka","house":6,"floor":4,"flat":90},"productList":[{"type":"Orange","price":1,"title":"апельсины","withBones":true},{"type":"Apple","price":1,"title":"яблоки","color":"green"}]},{"id":90,"address":{"country":"Russia","city":"Moscow","street":"Polyanka","house":6,"floor":4,"flat":91},"productList":[{"type":"Orange","price":1,"title":"апельсины","withBones":true},{"type":"Apple","price":1,"title":"яблоки","color":"green"}]},{"id":91,"address":{"country":"Russia","city":"Moscow","street":"Polyanka","house":6,"floor":4,"flat":92},"productList":[{"type":"Orange","price":1,"title":"апельсины","withBones":true},{"type":"Apple","price":1,"title":"яблоки","color":"green"}]},{"id":92,"address":{"country":"Russia","city":"Moscow","street":"Polyanka","house":6,"floor":4,"flat":93},"productList":[{"type":"Orange","price":1,"title":"апельсины","withBones":true},{"type":"Apple","price":1,"title":"яблоки","color":"green"}]},{"id":93,"address":{"country":"Russia","city":"Moscow","street":"Polyanka","house":6,"floor":4,"flat":94},"productList":[{"type":"Orange","price":1,"title":"апельсины","withBones":true},{"type":"Apple","price":1,"title":"яблоки","color":"green"}]},{"id":94,"address":{"country":"Russia","city":"Moscow","street":"Polyanka","house":6,"floor":4,"flat":95},"productList":[{"type":"Orange","price":1,"title":"апельсины","withBones":true},{"type":"Apple","price":1,"title":"яблоки","color":"green"}]},{"id":95,"address":{"country":"Russia","city":"Moscow","street":"Polyanka","house":6,"floor":4,"flat":96},"productList":[{"type":"Orange","price":1,"title":"апельсины","withBones":true},{"type":"Apple","price":1,"title":"яблоки","color":"green"}]},{"id":96,"address":{"country":"Russia","city":"Moscow","street":"Polyanka","house":6,"floor":4,"flat":97},"productList":[{"type":"Orange","price":1,"title":"апельсины","withBones":true},{"type":"Apple","price":1,"title":"яблоки","color":"green"}]},{"id":97,"address":{"country":"Russia","city":"Moscow","street":"Polyanka","house":6,"floor":4,"flat":98},"productList":[{"type":"Orange","price":1,"title":"апельсины","withBones":true},{"type":"Apple","price":1,"title":"яблоки","color":"green"}]},{"id":98,"address":{"country":"Russia","city":"Moscow","street":"Polyanka","house":6,"floor":4,"flat":99},"productList":[{"type":"Orange","price":1,"title":"апельсины","withBones":true},{"type":"Apple","price":1,"title":"яблоки","color":"green"}]},{"id":99,"address":{"country":"Russia","city":"Moscow","street":"Polyanka","house":6,"floor":4,"flat":100},"productList":[{"type":"Orange","price":1,"title":"апельсины","withBones":true},{"type":"Apple","price":1,"title":"яблоки","color":"green"}]}]